[
  {
    "question": "このみせでは、<strong>はんばい</strong>しているやさいがとてもあたらしいです。",
    "answer": "この店では、<strong>販売</strong>している野菜がとても新しいです。"
  },
  {
    "question": "<strong>しはん</strong>のくすりは、どこのやっきょくでもかえます。",
    "answer": "<strong>市販</strong>の薬は、どこの薬局でも買えます。"
  },
  {
    "question": "えきまえで<strong>ていしゃ</strong>するときは、じかんをまもってください。",
    "answer": "駅前で<strong>停車</strong>するときは、時間を守ってください。"
  },
  {
    "question": "このエリアでは、くるまの<strong>ていし</strong>がきんじられています。",
    "answer": "このエリアでは、車の<strong>停止</strong>が禁止されています。"
  },
  {
    "question": "ここは<strong>きんえん</strong>せきです。たばこをすわないでください。",
    "answer": "ここは<strong>禁煙</strong>席です。タバコを吸わないでください。"
  },
  {
    "question": "こうえんでのはしりは<strong>きんし</strong>されています。",
    "answer": "公園での走りは<strong>禁止</strong>されています。"
  },
  {
    "question": "このはなの<strong>かおり</strong>は、とてもすてきです。",
    "answer": "この花の<strong>香り</strong>は、とても素敵です。"
  },
  {
    "question": "コーヒーのにおいがよく<strong>かおる</strong>へやです。",
    "answer": "コーヒーの匂いがよく<strong>香る</strong>部屋です。"
  },
  {
    "question": "かのじょは、<strong>こうすい</strong>をいつもつけています。",
    "answer": "彼女は、<strong>香水</strong>をいつもつけています。"
  },
  {
    "question": "このおてらは、<strong>こくほう</strong>にしていされています。",
    "answer": "このお寺は、<strong>国宝</strong>に指定されています。"
  },
  {
    "question": "このむかしばなしには、かくされた<strong>たから</strong>がでてきます。",
    "answer": "この昔話には、隠された<strong>宝</strong>が出てきます。"
  }
]
