[
  {
    "question": "<strong>きみ</strong>のいえはどこですか。",
    "answer": "<strong>君</strong>の家はどこですか。"
  },
  {
    "question": "むかしの<strong>くんしゅ</strong>はけらいをしたがえた。",
    "answer": "昔の<strong>君主</strong>は家来を従えた。"
  },
  {
    "question": "あのふたりはかおが<strong>にる</strong>。",
    "answer": "あの二人は顔が<strong>似る</strong>。"
  },
  {
    "question": "こどもがおとなの<strong>まねする</strong>。",
    "answer": "子どもが大人の<strong>真似する</strong>。"
  },
  {
    "question": "このりょうしゃには<strong>るいじてん</strong>がある。",
    "answer": "この両者には<strong>類似点</strong>がある。"
  },
  {
    "question": "この<strong>ほど</strong>のさむさははじめてだ。",
    "answer": "この<strong>程</strong>の寒さは初めてだ。"
  },
  {
    "question": "このもんだいの<strong>ていど</strong>をはかってください。",
    "answer": "この問題の<strong>程度</strong>を測ってください。"
  },
  {
    "question": "らいしゅうの<strong>にってい</strong>をきめましょう。",
    "answer": "来週の<strong>日程</strong>を決めましょう。"
  },
  {
    "question": "がっこうの<strong>せいと</strong>は50にんです。",
    "answer": "学校の<strong>生徒</strong>は50人です。"
  },
  {
    "question": "えきまで<strong>とほ</strong>で5ふんです。",
    "answer": "駅まで<strong>徒歩</strong>で5分です。"
  },
  {
    "question": "このがくせいの<strong>せいせき</strong>はとてもいい。",
    "answer": "この学生の<strong>成績</strong>はとてもいい。"
  },
  {
    "question": "かれの<strong>じっせき</strong>はみとめられている。",
    "answer": "彼の<strong>実績</strong>は認められている。"
  },
  {
    "question": "かいしゃの<strong>ぎょうせき</strong>があがった。",
    "answer": "会社の<strong>業績</strong>が上がった。"
  },
  {
    "question": "このかわの<strong>きよい</strong>みずをのむ。",
    "answer": "この川の<strong>清い</strong>水を飲む。"
  },
  {
    "question": "こころが<strong>きよまる</strong>。",
    "answer": "心が<strong>清まる</strong>。"
  },
  {
    "question": "あいだのおかねを<strong>せいさん</strong>する。",
    "answer": "間のお金を<strong>清算</strong>する。"
  },
  {
    "question": "まいあさこうえんの<strong>せいそう</strong>をしています。",
    "answer": "毎朝公園の<strong>清掃</strong>をしています。"
  },
  {
    "question": "へやの<strong>そうじ</strong>をおわらせました。",
    "answer": "部屋の<strong>掃除</strong>を終わらせました。"
  },
  {
    "question": "ちりとりでごみを<strong>はく</strong>。",
    "answer": "ちりとりでごみを<strong>掃く</strong>。"
  },
  {
    "question": "このほんにはせいかくな<strong>きじゅつ</strong>があります。",
    "answer": "この本には正確な<strong>記述</strong>があります。"
  },
  {
    "question": "じぶんのいけんを<strong>のべる</strong>。",
    "answer": "自分の意見を<strong>述べる</strong>。"
  },
  {
    "question": "しょうげきてきな<strong>きょうじゅつ</strong>をききました。",
    "answer": "衝撃的な<strong>供述</strong>を聞きました。"
  },
  {
    "question": "へやの<strong>すみ</strong>にほんがおいてあります。",
    "answer": "部屋の<strong>隅</strong>に本が置いてあります。"
  },
  {
    "question": "へやの<strong>いちぐう</strong>にいすをおきました。",
    "answer": "部屋の<strong>一隅</strong>に椅子を置きました。"
  },
  {
    "question": "この<strong>ちいき</strong>はしずかです。",
    "answer": "この<strong>地域</strong>は静かです。"
  },
  {
    "question": "としょかんはしずかな<strong>くいき</strong>にあります。",
    "answer": "図書館は静かな<strong>区域</strong>にあります。"
  },
  {
    "question": "この<strong>りゅういき</strong>ではさかながたくさんとれます。",
    "answer": "この<strong>流域</strong>では魚がたくさん取れます。"
  },
  {
    "question": "あいてと<strong>きょうそう</strong>するのがすきです。",
    "answer": "相手と<strong>競争</strong>するのが好きです。"
  },
  {
    "question": "だれがはやいか<strong>きそう</strong>。",
    "answer": "誰が早いか<strong>競う</strong>。"
  },
  {
    "question": "オークションで<strong>せる</strong>。",
    "answer": "オークションで<strong>競る</strong>。"
  },
  {
    "question": "スポーツの<strong>きょうぎ</strong>をみます。",
    "answer": "スポーツの<strong>競技</strong>を見ます。"
  },
  {
    "question": "にちようびに<strong>けいば</strong>をみにいきます。",
    "answer": "日曜日に<strong>競馬</strong>を見に行きます。"
  },
  {
    "question": "おてらで<strong>きがん</strong>をおこないます。",
    "answer": "お寺で<strong>祈願</strong>を行います。"
  },
  {
    "question": "みんなのしあわせを<strong>いのる</strong>。",
    "answer": "みんなの幸せを<strong>祈る</strong>。"
  },
  {
    "question": "このたてものは<strong>きねん</strong>のためにたてられました。",
    "answer": "この建物は<strong>記念</strong>のために建てられました。"
  },
  {
    "question": "えきのまえに<strong>りっさつ</strong>がたっています。",
    "answer": "駅の前に<strong>立札</strong>が立っています。"
  },
  {
    "question": "ぎんこうで<strong>さつたば</strong>をうけとりました。",
    "answer": "銀行で<strong>札束</strong>を受け取りました。"
  },
  {
    "question": "この<strong>げきじょう</strong>ではいろいろなえんげきがひらかれます。",
    "answer": "この<strong>劇場</strong>ではいろいろな演劇が開かれます。"
  },
  {
    "question": "にほんの<strong>えんげき</strong>をみにいきました。",
    "answer": "日本の<strong>演劇</strong>を見に行きました。"
  },
  {
    "question": "この<strong>きげき</strong>はとてもおもしろかったです。",
    "answer": "この<strong>喜劇</strong>はとても面白かったです。"
  },
  {
    "question": "あしたのてんきを<strong>よそく</strong>する。",
    "answer": "明日の天気を<strong>予測</strong>する。"
  },
  {
    "question": "ものさしでながさを<strong>はかる</strong>。",
    "answer": "物差しで長さを<strong>測る</strong>。"
  },
  {
    "question": "てんたいを<strong>かんそく</strong>する。",
    "answer": "天体を<strong>観測</strong>する。"
  },
  {
    "question": "がっこうには<strong>きりつ</strong>があります。",
    "answer": "学校には<strong>規律</strong>があります。"
  },
  {
    "question": "おてらには<strong>かいりつ</strong>があります。",
    "answer": "お寺には<strong>戒律</strong>があります。"
  },
  {
    "question": "かのじょの<strong>あしわざ</strong>はすばらしい。",
    "answer": "彼女の<strong>足技</strong>は素晴らしい。"
  },
  {
    "question": "わたしの<strong>とくぎ</strong>はすいえいです。",
    "answer": "私の<strong>特技</strong>は水泳です。"
  },
  {
    "question": "この<strong>ほうりつ</strong>はらいねんからしかたがかわります。",
    "answer": "この<strong>法律</strong>は来年から仕方が変わります。"
  },
  {
    "question": "この<strong>ぎじゅつ</strong>はむずかしいです。",
    "answer": "この<strong>技術</strong>は難しいです。"
  },
  {
    "question": "あめでかばんが<strong>しめる</strong>。",
    "answer": "雨で鞄が<strong>湿る</strong>。"
  },
  {
    "question": "ぬれたてを<strong>しめす</strong>。",
    "answer": "濡れた手を<strong>湿す</strong>。"
  },
  {
    "question": "なつは<strong>しっけ</strong>がおおいです。",
    "answer": "夏は<strong>湿気</strong>が多いです。"
  },
  {
    "question": "このほんの<strong>しょはん</strong>はとてもめずらしいです。",
    "answer": "この本の<strong>初版</strong>はとても珍しいです。"
  },
  {
    "question": "この<strong>はんが</strong>はうつくしいです。",
    "answer": "この<strong>版画</strong>は美しいです。"
  },
  {
    "question": "あたらしいほんを<strong>しゅっぱん</strong>しました。",
    "answer": "新しい本を<strong>出版</strong>しました。"
  }
]
